minotorr/__init__.py
minotorr/cpu.py
minotorr/gpu.py
minotorr/minotorr.py
minotorr/ram.py
minotorr-0.7.1.dist-info/LICENSE
minotorr-0.7.1.dist-info/METADATA
minotorr-0.7.1.dist-info/WHEEL
minotorr-0.7.1.dist-info/top_level.txt
minotorr-0.7.1.dist-info/RECORD
