Metadata-Version: 2.1
Name: minotorr
Version: 0.7.1
Summary: Unofficial Libre Hardware Monitor python client
Home-page: https://github.com/Gokender/minotorr
Author: gokender
Author-email: gauthier.chaty+pypi@outlook.com
License: UNKNOWN
Platform: UNKNOWN
Classifier: Programming Language :: Python :: 3
Classifier: License :: OSI Approved :: MIT License
Classifier: Operating System :: OS Independent
Requires-Python: >=3.6
Requires-Dist: requests
